quiltsync/.DS_Store
quiltsync/AboutScreen/__init__.py
quiltsync/AboutScreen/about_screen.kv
quiltsync/AboutScreen/about_screen.py
quiltsync/LoginScreen/__init__.py
quiltsync/LoginScreen/login_screen.kv
quiltsync/LoginScreen/login_screen.py
quiltsync/Package/package_screen.kv
quiltsync/Package/package_screen.py
quiltsync/Resource/confirm.py
quiltsync/Resource/resource.py
quiltsync/Resource/resource_edit_screen.kv
quiltsync/Resource/resource_edit_screen.py
quiltsync/Resource/resource_list_screen.kv
quiltsync/Resource/resource_list_screen.py
quiltsync/__init__.py
quiltsync/apputils.py
quiltsync/client.py
quiltsync/main.ini
quiltsync/main.py
quiltsync/mainapp.kv
quiltsync-0.1.1.dist-info/LICENSE.md
quiltsync-0.1.1.dist-info/WHEEL
quiltsync-0.1.1.dist-info/entry_points.txt
quiltsync-0.1.1.dist-info/METADATA
quiltsync-0.1.1.dist-info/RECORD
