Metadata-Version: 2.1
Name: quiltsync
Version: 0.1.1
Summary: Graphical desktop client to sync Quilt data packages between local filesystems and cloud object stores
Author: Ernest Prabhakar
Author-email: ernest@quiltdata.io
Requires-Python: >=3.10,<4.0
Classifier: Programming Language :: Python :: 3
Classifier: Programming Language :: Python :: 3.10
Classifier: Programming Language :: Python :: 3.11
Requires-Dist: httpx (>=0.23.3,<0.24.0)
Requires-Dist: kivymd (>=1.1.1,<2.0.0)
Requires-Dist: quiltplus (>=0.6.0,<0.7.0)
Requires-Dist: trio (>=0.22.0,<0.23.0)
